tweebot/__init__.py
tweebot/_base.py
tweebot/actions.py
tweebot/agents.py
tweebot/bot.py
tweebot/constants.py
tweebot/handlers.py
twitter_bot.egg-info/PKG-INFO
twitter_bot.egg-info/SOURCES.txt
twitter_bot.egg-info/dependency_links.txt
twitter_bot.egg-info/requires.txt
twitter_bot.egg-info/top_level.txt
twitter_bot-0.1.dist-info/METADATA
twitter_bot-0.1.dist-info/WHEEL
twitter_bot-0.1.dist-info/top_level.txt
twitter_bot-0.1.dist-info/RECORD
